README.md
cherries
setup.py
cherries/
cherries/__init__.py
cherries/range_set.py
cherries.egg-info/PKG-INFO
cherries.egg-info/SOURCES.txt
cherries.egg-info/dependency_links.txt
cherries.egg-info/top_level.txt